setup.py
hbm_distributions/Binomialdistribution.py
hbm_distributions/Gaussiandistribution.py
hbm_distributions/Generaldistribution.py
hbm_distributions/__init__.py
hbm_distributions.egg-info/PKG-INFO
hbm_distributions.egg-info/SOURCES.txt
hbm_distributions.egg-info/dependency_links.txt
hbm_distributions.egg-info/not-zip-safe
hbm_distributions.egg-info/top_level.txt