Metadata-Version: 1.0
Name: hbm-distributions
Version: 1.0
Summary: Gaussian distributions
Home-page: UNKNOWN
Author: Hwi Moon
Author-email: hbmoon@berkeley.edu
License: UNKNOWN
Platform: UNKNOWN
